vasppy/__init__.py
vasppy/atom.py
vasppy/band.py
vasppy/calculation.py
vasppy/cell.py
vasppy/configuration.py
vasppy/doscar.py
vasppy/grid.py
vasppy/kpoints.py
vasppy/neighbour_list.py
vasppy/optics.py
vasppy/outcar.py
vasppy/pimaim.py
vasppy/polyhedron.py
vasppy/poscar.py
vasppy/procar.py
vasppy/rdf.py
vasppy/summary.py
vasppy/units.py
vasppy/utils.py
vasppy/vaspmeta.py
vasppy/vasprun.py
vasppy/version.py
vasppy/xdatcar.py
vasppy/data/GGA_md5.yaml
vasppy/data/GGA_nelect.yaml
vasppy/data/LDA_52_md5.yaml
vasppy/data/LDA_52_nelect.yaml
vasppy/data/LDA_54_md5.yaml
vasppy/data/LDA_54_nelect.yaml
vasppy/data/LDA_54r_md5.yaml
vasppy/data/LDA_54r_nelect.yaml
vasppy/data/LDA_md5.yaml
vasppy/data/LDA_nelect.yaml
vasppy/data/PBE_52_md5.yaml
vasppy/data/PBE_52_nelect.yaml
vasppy/data/PBE_54_md5.yaml
vasppy/data/PBE_54_nelect.yaml
vasppy/data/PBE_54r_md5.yaml
vasppy/data/PBE_54r_nelect.yaml
vasppy/data/PBE_md5.yaml
vasppy/data/PBE_nelect.yaml
vasppy/data/USPP_GGA_md5.yaml
vasppy/data/USPP_GGA_nelect.yaml
vasppy/data/USPP_LDA_md5.yaml
vasppy/data/USPP_LDA_nelect.yaml
vasppy/data/__init__.py
vasppy/data/potcar_data.py
vasppy/scripts/__init__.py
vasppy/scripts/check_species.py
vasppy/scripts/effective_mass.py
vasppy/scripts/fat_bands.py
vasppy/scripts/murnfit.py
vasppy/scripts/pimaim_to_poscar.py
vasppy/scripts/pimaim_to_xtl.py
vasppy/scripts/poscar_sort.py
vasppy/scripts/poscar_to_cif.py
vasppy/scripts/poscar_to_pimaim.py
vasppy/scripts/poscar_to_xtl.py
vasppy/scripts/potcar_spec.py
vasppy/scripts/proc_poscar.py
vasppy/scripts/rotate_poscar.py
vasppy/scripts/spacegroup.py
vasppy/scripts/vasp_grid.py
vasppy/scripts/vasp_summary.py
vasppy/scripts/xdatcar_to_disp.py
vasppy/scripts/xdatcar_to_rdf.py
vasppy-0.7.1.0.dist-info/LICENSE
vasppy-0.7.1.0.dist-info/METADATA
vasppy-0.7.1.0.dist-info/WHEEL
vasppy-0.7.1.0.dist-info/entry_points.txt
vasppy-0.7.1.0.dist-info/top_level.txt
vasppy-0.7.1.0.dist-info/RECORD
