Metadata-Version: 2.1
Name: vasppy
Version: 0.7.1.0
Summary: Python utilities for working with VASP inputs and outputs
Home-page: https://github.com/bjmorgan/vasppy
Author: Benjamin J. Morgan
Author-email: bjm42@bath.ac.uk
License: MIT
Download-URL: https://github.com/bjmorgan/vasppy/archive/0.7.1.0.tar.gz
Keywords: vasp
Platform: UNKNOWN
Requires-Python: >=3.7
Requires-Dist: monty
Requires-Dist: numpy (>=1.16.2)
Requires-Dist: pandas
Requires-Dist: pymatgen (>=2022.0.0)
Requires-Dist: PyYAML
Requires-Dist: coverage (==4.3.4)
Requires-Dist: codeclimate-test-reporter
Requires-Dist: fortranformat
Requires-Dist: scipy (>=1.4.1)
Requires-Dist: tqdm
Requires-Dist: lxml
